Verilog Modules/PE.v
module PE #(
    parameter n = 10,  //preferably larger to hold peak value(n=20)
    parameter CHARWIDTH = 2, 
    parameter signed match = 2, 
    parameter signed mismatch = -1,
    parameter signed loss = -1  
)(  input clk,
    input load,
    input rst,
    input [1:0] char_in, // A, G ,T ,C
    input signed [n:0] E_in,     //left input
    input signed[n:0] F_in,     //up input 
    input signed[n:0] G_in,     //diagonal input 
    input [CHARWIDTH-1:0] S_in,     //secondary string      
    output reg signed [n:0] H_curr,
    output reg signed [n:0] H_delay,
    output reg [CHARWIDTH-1:0] S_out,
    output reg [CHARWIDTH-1:0] char_out
);
reg [CHARWIDTH-1:0] Q_pe;
wire signed [n:0] E_temp, F_temp, G_temp, H_temp;
assign E_temp = E_in+loss;
assign F_temp = F_in+loss;
assign G_temp = (Q_pe == S_in) ? (G_in + match) : (G_in + mismatch);
wire signed [n:0] max_val = (E_temp > F_temp) ? E_temp : F_temp;
wire signed [n:0] max_with_G = (max_val > G_temp) ? max_val : G_temp;
assign H_temp = (max_with_G > 0) ? max_with_G : 0;   

always@(posedge clk) begin
    if (rst) begin
        H_curr <= 0;
        H_delay <= 0;
        S_out <= 0;
        Q_pe <= 0;
        char_out <= 0;

    end else if(load) begin 
        Q_pe <= char_in;
        char_out <= Q_pe;

    end else begin 
        S_out <= S_in;
        H_delay <= H_curr;
        H_curr <= H_temp;
    end 
end 
endmodule

Verilog Modules/Genvar_wrapper.v
module Genvar_wrapper #(
    parameter n = 10, //preferably larger to hold peak value(n=20)
    parameter loaded_string_size = 4 
)(
    input clk,
    input load,
    input rst,
    input [2*loaded_string_size-1:0] loaded_string,
    input [1:0] S_char_in,
    output wire [(n+1)*loaded_string_size-1 : 0] all_scores    
);

wire signed [n:0] H_curr [0:loaded_string_size-1];
wire signed [n:0] H_delay [0:loaded_string_size-1];
wire [1:0] S_out [0:loaded_string_size-1];
wire [1:0] char_out [0:loaded_string_size-1];

genvar i;
generate
    for( i=0; i<loaded_string_size; i=i+1)begin : PE_GEN
        if(i==0) begin
            PE #(.n(n)) pe (
                .clk(clk),
                .load(load),
                .rst(rst),
                .char_in(loaded_string[1:0]),
                .E_in({(n+1){1'b0}}),
                .F_in({(n+1){1'b0}}),
                .G_in({(n+1){1'b0}}),
                .S_in(S_char_in),
                .H_curr(H_curr[i]),
                .H_delay(H_delay[i]),
                .S_out(S_out[i]),
                .char_out(char_out[i])
            );
        end else begin 
            PE #(.n(n)) pe (
                .clk(clk),
                .load(load),
                .rst(rst),
                .char_in(loaded_string[2*i+1:2*i]),
                .E_in(H_curr[i-1]),
                .F_in(H_curr[i]),
                .G_in(H_delay[i-1]),
                .S_in(S_out[i-1]),
                .H_curr(H_curr[i]),
                .H_delay(H_delay[i]),
                .S_out(S_out[i]),
                .char_out(char_out[i])
            );
        end

        assign all_scores[i*(n+1) +: (n+1)] = H_curr[i];
    end
endgenerate
endmodule

Verilog Modules/Genvar_tb.v
`timescale 1ns/1ps

module Genvar_tb;
    parameter N = 10; // Score bit-width
    parameter L = 4;  // Number of PEs (Query Length)
    
    reg clk, rst, load;
    reg [2*L-1:0] query_string;
    reg [1:0] s_char_in;
    wire [(N+1)*L-1:0] all_scores;

    // Instantiate the Wrapper
    Genvar_wrapper #(.n(N), .loaded_string_size(L)) uut (
        .clk(clk),
        .rst(rst),
        .load(load),
        .loaded_string(query_string),
        .S_char_in(s_char_in),
        .all_scores(all_scores)
    );

    // Clock Generation
    always #5 clk = ~clk;

    initial begin
        // --- Initialization ---
        clk = 0; rst = 1; load = 0; s_char_in = 0;
        query_string = 8'b11_10_01_00; // Example Query: T(11) G(10) C(01) A(00)
        
        $dumpfile("Genvar_sim.vcd");
        $dumpvars(0, Genvar_tb);

        #15 rst = 0;
        
        // --- Phase 1: Loading the Query ---
        // In your parallel-load code, this happens instantly
        $display("Time: %0t | Loading Query...", $time);
        #10 load = 1; 
        #10 load = 0; 

        // --- Phase 2: Streaming the Subject ---
        // We will stream "AGTC" (00, 10, 01, 11) one by one
        $display("Time: %0t | Starting Wavefront Stream...", $time);
        
        // Stream 'A' (00)
        s_char_in = 2'b00; #10; 
        // Stream 'G' (10)
        s_char_in = 2'b10; #10;
        // Stream 'C' (01)
        s_char_in = 2'b01; #10;
        // Stream 'T' (11)
        s_char_in = 2'b11; #10;
        
        // Final flush cycles to let the wave exit the last PE
        s_char_in = 2'b00; 
        repeat(L+2) #10;

        $display("Time: %0t | Simulation Finished.", $time);
        $finish;
    end

    // Monitor the scores for debugging
    initial begin
        $monitor("T=%0t | S_in=%b | Scores: %h", $time, s_char_in, all_scores);
    end

endmodule

sim/Genvar/Genvar_sim.vcd
$date
	Sat Mar 21 03:55:36 2026
$end
$version
	Icarus Verilog
$end
$timescale
	1ps
$end
$scope module Genvar_tb $end
$var wire 44 ! all_scores [43:0] $end
$var parameter 32 " L $end
$var parameter 32 # N $end
$var reg 1 $ clk $end
$var reg 1 % load $end
$var reg 8 & query_string [7:0] $end
$var reg 1 ' rst $end
$var reg 2 ( s_char_in [1:0] $end
$scope module uut $end
$var wire 2 ) S_char_in [1:0] $end
$var wire 1 $ clk $end
$var wire 1 % load $end
$var wire 8 * loaded_string [7:0] $end
$var wire 1 ' rst $end
$var wire 44 + all_scores [43:0] $end
$var parameter 32 , loaded_string_size $end
$var parameter 32 - n $end
$scope begin PE_GEN[0] $end
$var parameter 2 . i $end
$scope begin genblk1 $end
$scope module pe $end
$var wire 11 / E_in [10:0] $end
$var wire 11 0 F_in [10:0] $end
$var wire 11 1 G_in [10:0] $end
$var wire 2 2 S_in [1:0] $end
$var wire 2 3 char_in [1:0] $end
$var wire 1 $ clk $end
$var wire 1 % load $end
$var wire 1 ' rst $end
$var wire 11 4 max_with_G [10:0] $end
$var wire 11 5 max_val [10:0] $end
$var wire 11 6 H_temp [10:0] $end
$var wire 11 7 G_temp [10:0] $end
$var wire 11 8 F_temp [10:0] $end
$var wire 11 9 E_temp [10:0] $end
$var parameter 32 : CHARWIDTH $end
$var parameter 32 ; loss $end
$var parameter 32 < match $end
$var parameter 32 = mismatch $end
$var parameter 32 > n $end
$var reg 11 ? H_curr [10:0] $end
$var reg 11 @ H_delay [10:0] $end
$var reg 2 A Q_pe [1:0] $end
$var reg 2 B S_out [1:0] $end
$var reg 2 C char_out [1:0] $end
$upscope $end
$upscope $end
$upscope $end
$scope begin PE_GEN[1] $end
$var parameter 2 D i $end
$scope begin genblk1 $end
$scope module pe $end
$var wire 11 E E_in [10:0] $end
$var wire 11 F G_in [10:0] $end
$var wire 2 G S_in [1:0] $end
$var wire 2 H char_in [1:0] $end
$var wire 1 $ clk $end
$var wire 1 % load $end
$var wire 1 ' rst $end
$var wire 11 I max_with_G [10:0] $end
$var wire 11 J max_val [10:0] $end
$var wire 11 K H_temp [10:0] $end
$var wire 11 L G_temp [10:0] $end
$var wire 11 M F_temp [10:0] $end
$var wire 11 N F_in [10:0] $end
$var wire 11 O E_temp [10:0] $end
$var parameter 32 P CHARWIDTH $end
$var parameter 32 Q loss $end
$var parameter 32 R match $end
$var parameter 32 S mismatch $end
$var parameter 32 T n $end
$var reg 11 U H_curr [10:0] $end
$var reg 11 V H_delay [10:0] $end
$var reg 2 W Q_pe [1:0] $end
$var reg 2 X S_out [1:0] $end
$var reg 2 Y char_out [1:0] $end
$upscope $end
$upscope $end
$upscope $end
$scope begin PE_GEN[2] $end
$var parameter 3 Z i $end
$scope begin genblk1 $end
$scope module pe $end
$var wire 11 [ E_in [10:0] $end
$var wire 11 \ G_in [10:0] $end
$var wire 2 ] S_in [1:0] $end
$var wire 2 ^ char_in [1:0] $end
$var wire 1 $ clk $end
$var wire 1 % load $end
$var wire 1 ' rst $end
$var wire 11 _ max_with_G [10:0] $end
$var wire 11 ` max_val [10:0] $end
$var wire 11 a H_temp [10:0] $end
$var wire 11 b G_temp [10:0] $end
$var wire 11 c F_temp [10:0] $end
$var wire 11 d F_in [10:0] $end
$var wire 11 e E_temp [10:0] $end
$var parameter 32 f CHARWIDTH $end
$var parameter 32 g loss $end
$var parameter 32 h match $end
$var parameter 32 i mismatch $end
$var parameter 32 j n $end
$var reg 11 k H_curr [10:0] $end
$var reg 11 l H_delay [10:0] $end
$var reg 2 m Q_pe [1:0] $end
$var reg 2 n S_out [1:0] $end
$var reg 2 o char_out [1:0] $end
$upscope $end
$upscope $end
$upscope $end
$scope begin PE_GEN[3] $end
$var parameter 3 p i $end
$scope begin genblk1 $end
$scope module pe $end
$var wire 11 q E_in [10:0] $end
$var wire 11 r G_in [10:0] $end
$var wire 2 s S_in [1:0] $end
$var wire 2 t char_in [1:0] $end
$var wire 1 $ clk $end
$var wire 1 % load $end
$var wire 1 ' rst $end
$var wire 11 u max_with_G [10:0] $end
$var wire 11 v max_val [10:0] $end
$var wire 11 w H_temp [10:0] $end
$var wire 11 x G_temp [10:0] $end
$var wire 11 y F_temp [10:0] $end
$var wire 11 z F_in [10:0] $end
$var wire 11 { E_temp [10:0] $end
$var parameter 32 | CHARWIDTH $end
$var parameter 32 } loss $end
$var parameter 32 ~ match $end
$var parameter 32 !" mismatch $end
$var parameter 32 "" n $end
$var reg 11 #" H_curr [10:0] $end
$var reg 11 $" H_delay [10:0] $end
$var reg 2 %" Q_pe [1:0] $end
$var reg 2 &" S_out [1:0] $end
$var reg 2 '" char_out [1:0] $end
$upscope $end
$upscope $end
$upscope $end
$upscope $end
$upscope $end
$enddefinitions $end
$comment Show the parameter values. $end
$dumpall
b1010 ""
b11111111111111111111111111111111 !"
b10 ~
b11111111111111111111111111111111 }
b10 |
b11 p
b1010 j
b11111111111111111111111111111111 i
b10 h
b11111111111111111111111111111111 g
b10 f
b10 Z
b1010 T
b11111111111111111111111111111111 S
b10 R
b11111111111111111111111111111111 Q
b10 P
b1 D
b1010 >
b11111111111111111111111111111111 =
b10 <
b11111111111111111111111111111111 ;
b10 :
b0 .
b1010 -
b100 ,
b1010 #
b100 "
$end
#0
$dumpvars
bx '"
bx &"
bx %"
bx $"
bx #"
bx {
bx z
bx y
bx x
bx w
bx v
bx u
b11 t
bx s
bx r
bx q
bx o
bx n
bx m
bx l
bx k
bx e
bx d
bx c
bx b
bx a
bx `
bx _
b10 ^
bx ]
bx \
bx [
bx Y
bx X
bx W
bx V
bx U
bx O
bx N
bx M
bx L
bx K
bx J
bx I
b1 H
bx G
bx F
bx E
bx C
bx B
bx A
bx @
bx ?
b11111111111 9
b11111111111 8
bx1x 7
bx 6
b11111111111 5
bx1x 4
b0 3
b0 2
b0 1
b0 0
b0 /
bx +
b11100100 *
b0 )
b0 (
1'
b11100100 &
0%
0$
bx !
$end
#5000
b10 6
b10 K
b10 a
b10 w
b10 4
b10 I
b10 _
b10 u
b10 7
b10 L
b10 b
b11111111111 J
b10 x
b11111111111 `
b11111111111 v
b11111111111 O
b11111111111 M
b11111111111 e
b11111111111 c
b11111111111 {
b11111111111 y
b0 C
b0 A
b0 B
b0 G
b0 @
b0 F
b0 ?
b0 E
b0 Y
b0 W
b0 X
b0 ]
b0 V
b0 \
b0 N
b0 U
b0 [
b0 o
b0 m
b0 n
b0 s
b0 l
b0 r
b0 d
b0 k
b0 q
b0 '"
b0 %"
b0 &"
b0 $"
b0 !
b0 +
b0 z
b0 #"
1$
#10000
0$
#15000
b1 v
b1 `
b1 J
b1 y
b1 c
b1 {
b1 M
b1 e
b1 O
b10 z
b10 #"
b10 d
b10 k
b10 q
b10 N
b10 U
b10 [
b10000000000100000000001000000000010 !
b10000000000100000000001000000000010 +
b10 ?
b10 E
1$
0'
#20000
0$
#25000
b1 K
b1 a
b1 w
b1 I
b1 _
b1 u
b11111111111 L
b11111111111 b
b11111111111 x
b1 W
b10 m
b11 %"
1$
1%
#30000
0$
#35000
b0 v
b0 `
b1 x
b1 b
b1 L
b0 y
b0 c
b0 {
b0 M
b0 e
b1 z
b1 #"
b10 $"
b1 d
b1 k
b1 q
b10 l
b10 r
b1000000000010000000000100000000010 !
b1000000000010000000000100000000010 +
b1 N
b1 U
b1 [
b10 V
b10 \
b10 @
b10 F
1$
0%
#40000
0$
#45000
b0 a
b0 w
b0 _
b0 u
b0 b
b0 x
b10 B
b10 G
b1 V
b1 \
b1 l
b1 r
b1 $"
b0 6
b11111111111 4
b11111111111 7
1$
b10 (
b10 )
b10 2
#50000
0$
#55000
b11 a
b100 K
b11 _
b100 I
b11111111111 v
b11 b
b0 J
b100 L
b11111111111 y
b11111111111 c
b11111111111 {
b11111111111 O
b0 z
b0 #"
b0 d
b0 k
b0 q
b10 X
b10 ]
b100000000000 !
b100000000000 +
b0 ?
b0 E
b1 B
b1 G
1$
b1 (
b1 )
b1 2
#60000
0$
#65000
b11 K
b10 w
b11 I
b10 u
b11111111111 L
b11 J
b0 b
b11 `
b10 v
b11111111111 x
b11 M
b11 e
b10 c
b10 {
b0 @
b0 F
b11 B
b11 G
b100 N
b100 U
b100 [
b1 X
b1 ]
b110000000010000000000000 !
b110000000010000000000000 +
b11 d
b11 k
b11 q
b0 l
b0 r
b10 n
b10 s
b0 $"
1$
b11 (
b11 )
b11 2
#70000
0$
#75000
b10 K
b10 I
b10 x
b10 J
b10 `
b11 b
b1 y
b10 M
b10 e
b10 z
b10 #"
b10 &"
b11 l
b11 r
b1 n
b1 s
b10000000000110000000001100000000000 !
b10000000000110000000001100000000000 +
b11 N
b11 U
b11 [
b100 V
b100 \
b11 X
b11 ]
b0 B
b0 G
b10 6
b10 4
b10 7
1$
b0 (
b0 )
b0 2
#80000
0$
#85000
b1 K
b10 a
b101 w
b1 I
b10 _
b101 u
b1 J
b10 b
b101 x
b1 O
b1 M
b1 e
b10 ?
b10 E
b10000000000110000000001000000000010 !
b10000000000110000000001000000000010 +
b10 N
b10 U
b10 [
b11 V
b11 \
b0 X
b0 ]
b11 n
b11 s
b10 $"
b1 &"
1$
#90000
0$
#95000
b100 w
b1 a
b100 u
b1 _
b1 `
b100 v
b10 x
b1 b
b1 L
b100 y
b1 c
b1 {
b0 M
b0 e
b101 z
b101 #"
b11 &"
b10 d
b10 k
b10 q
b0 n
b0 s
b101000000000100000000000100000000010 !
b101000000000100000000000100000000010 +
b1 N
b1 U
b1 [
b10 V
b10 \
b10 @
b10 F
1$
#100000
0$
#105000
b0 a
b11 w
b0 _
b11 u
b0 b
b0 `
b1 x
b11 v
b0 c
b0 {
b11 y
b1 V
b1 \
b1 d
b1 k
b1 q
b10 l
b10 r
b100000000000010000000000100000000010 !
b100000000000010000000000100000000010 +
b100 z
b100 #"
b101 $"
b0 &"
1$
#110000
0$
#115000
b10 w
b10 u
b10 v
b0 x
b10 y
b11111111111 c
b11111111111 {
b11 z
b11 #"
b100 $"
b11000000000000000000000100000000010 !
b11000000000000000000000100000000010 +
b0 d
b0 k
b0 q
b1 l
b1 r
1$
#120000
0$
#125000
b1 w
b1 u
b11111111111 x
b1 v
b1 y
b0 l
b0 r
b10000000000000000000000100000000010 !
b10000000000000000000000100000000010 +
b10 z
b10 #"
b11 $"
1$
#130000
0$
#135000
b0 w
b0 u
b0 v
b0 y
b1000000000000000000000100000000010 !
b1000000000000000000000100000000010 +
b1 z
b1 #"
b10 $"
1$
