PE/PE.v
module PE #(
    parameter n = 5,  //preferably larger to hold peak value(n=20)
    parameter CHARWIDTH = 2, 
    parameter signed match = 2, 
    parameter signed mismatch = -1,
    parameter signed loss = -1  
)(  input clk,
    input load,
    input rst,
    input [1:0] char_in, // A, G ,T ,C
    input signed [n:0] E_in,     //left input
    input signed[n:0] F_in,     //up input 
    input signed[n:0] G_in,     //diagonal input 
    input [CHARWIDTH-1:0] S_in,          
    output reg signed [n:0] H_curr,
    output reg signed [n:0] H_delay,
    output reg [CHARWIDTH-1:0] S_out,
    output reg [CHARWIDTH-1:0] char_out
);
reg [CHARWIDTH-1:0] Q_pe;
wire signed [n:0] E_temp, F_temp, G_temp, H_temp;
assign E_temp = E_in+loss;
assign F_temp = F_in+loss;
assign G_temp = (Q_pe == S_in) ? (G_in + match) : (G_in + mismatch);
assign H_temp = (E_temp > F_temp && E_temp > G_temp && E_temp >0) ? E_temp : 
                (F_temp > G_temp && F_temp > 0) ? F_temp : (G_temp > 0)? G_temp : 0;     

always@(posedge clk) begin
    if (rst) begin
        H_curr <= 0;
        H_delay <= 0;
        S_out <= 0;

    end else if(load) begin 
        Q_pe <= char_in;
        char_out <= Q_pe;

    end else begin 
        S_out <= S_in;
        H_delay <= H_curr;
        H_curr <= H_temp;
    end 
end 
endmodule

sim/PE/PE_check.v
`timescale 1ns/1ps

module PE_check;
    // Parameters matching your latest PE
    parameter n = 5; 
    parameter CHARWIDTH = 2;
    parameter CLK_PERIOD = 10;
    
    reg clk, rst, load;
    reg [1:0] char_in;
    reg signed [n:0] E_in, F_in, G_in;
    reg [CHARWIDTH-1:0] S_in;
    
    wire signed [n:0] H_curr, H_delay;
    wire [CHARWIDTH-1:0] S_out, char_out;

    // DUT Instance with your updated port list
    PE #(.n(n), .CHARWIDTH(CHARWIDTH)) dut (
        .clk(clk), 
        .rst(rst),
        .load(load),
        .char_in(char_in),
        .E_in(E_in), 
        .F_in(F_in), 
        .G_in(G_in), 
        .S_in(S_in),
        .H_curr(H_curr), 
        .H_delay(H_delay),
        .S_out(S_out),
        .char_out(char_out)
    );

    // Clock Generation
    initial begin
        clk = 0;
        forever #(CLK_PERIOD/2) clk = ~clk;
    end

    initial begin
        $dumpfile("PE_check.vcd");
        $dumpvars(0, PE_check);

        // --- PHASE 1: Reset ---
        $display("\n=== Starting Smith-Waterman PE Test ===");
        rst = 1; load = 0; char_in = 0;
        E_in = 0; F_in = 0; G_in = 0; S_in = 0;
        #(CLK_PERIOD * 2);
        rst = 0;
        $display("Status: Reset Complete");

        // --- PHASE 2: Load Query Character ---
        // Let's load '2' (e.g., 'T') into this PE
        @(posedge clk);
        load = 1;
        char_in = 2'b10; // Value 2
        @(posedge clk);
        load = 0;
        $display("Status: Loaded Q_pe = %0d", char_in);

        // --- PHASE 3: Match Test ---
        $display("\nTest 1: Match (S_in=2, Q_pe=2)");
        // Diagonal input (G_in) is 1. Match is +2.
        G_in = 1; S_in = 2'b10; 
        @(posedge clk); 
        #1; // Wait for logic to settle
        $display("  Input: G_in=%0d, Match=+2 | Output: H_curr=%0d (Expected: 3)", G_in, H_curr);

        // --- PHASE 4: Dependency & Delay Test ---
        $display("\nTest 2: Left Input & Delay Check");
        // E_in is 10. Loss is -1. Should result in 9.
        E_in = 10; S_in = 2'b01; // Mismatch with Q_pe(2)
        @(posedge clk);
        #1;
        $display("  Input: E_in=%0d, Loss=-1  | Output: H_curr=%0d (Expected: 9)", E_in, H_curr);
        $display("  Check: H_delay = %0d (Expected: 3 from previous cycle)", H_delay);

        // --- PHASE 5: Zero Floor (Local Alignment) ---
        $display("\nTest 3: Zero Floor Check");
        E_in = -5; F_in = -2; G_in = -10;
        @(posedge clk);
        #1;
        $display("  Input: All negative  | Output: H_curr=%0d (Expected: 0)", H_curr);

        $display("\n=== Simulation Complete ===\n");
        $finish;
    end
endmodule

PE/PE_check.vcd
$date
	Sat Mar 21 00:41:16 2026
$end
$version
	Icarus Verilog
$end
$timescale
	1ps
$end
$scope module PE_check $end
$var wire 2 ! char_out [1:0] $end
$var wire 2 " S_out [1:0] $end
$var wire 6 # H_delay [5:0] $end
$var wire 6 $ H_curr [5:0] $end
$var parameter 32 % CHARWIDTH $end
$var parameter 32 & CLK_PERIOD $end
$var parameter 32 ' n $end
$var reg 6 ( E_in [5:0] $end
$var reg 6 ) F_in [5:0] $end
$var reg 6 * G_in [5:0] $end
$var reg 2 + S_in [1:0] $end
$var reg 2 , char_in [1:0] $end
$var reg 1 - clk $end
$var reg 1 . load $end
$var reg 1 / rst $end
$scope module dut $end
$var wire 6 0 E_in [5:0] $end
$var wire 6 1 F_in [5:0] $end
$var wire 6 2 G_in [5:0] $end
$var wire 2 3 S_in [1:0] $end
$var wire 2 4 char_in [1:0] $end
$var wire 1 - clk $end
$var wire 1 . load $end
$var wire 1 / rst $end
$var wire 6 5 H_temp [5:0] $end
$var wire 6 6 G_temp [5:0] $end
$var wire 6 7 F_temp [5:0] $end
$var wire 6 8 E_temp [5:0] $end
$var parameter 32 9 CHARWIDTH $end
$var parameter 32 : loss $end
$var parameter 32 ; match $end
$var parameter 32 < mismatch $end
$var parameter 32 = n $end
$var reg 6 > H_curr [5:0] $end
$var reg 6 ? H_delay [5:0] $end
$var reg 2 @ Q_pe [1:0] $end
$var reg 2 A S_out [1:0] $end
$var reg 2 B char_out [1:0] $end
$upscope $end
$upscope $end
$enddefinitions $end
$comment Show the parameter values. $end
$dumpall
b101 =
b11111111111111111111111111111111 <
b10 ;
b11111111111111111111111111111111 :
b10 9
b101 '
b1010 &
b10 %
$end
#0
$dumpvars
bx B
bx A
bx @
bx ?
bx >
b111111 8
b111111 7
bx1x 6
bx 5
b0 4
b0 3
b0 2
b0 1
b0 0
1/
0.
0-
b0 ,
b0 +
b0 *
b0 )
b0 (
bx $
bx #
bx "
bx !
$end
#5000
b0 "
b0 A
b0 #
b0 ?
b0 $
b0 >
1-
#10000
0-
#15000
1-
#20000
0-
0/
#25000
b0 5
b111111 6
b10 @
b10 ,
b10 4
1.
1-
#30000
0-
#35000
b10 !
b10 B
b11 5
b11 6
b10 +
b10 3
b1 *
b1 2
0.
1-
#40000
0-
#45000
b11 $
b11 >
b10 "
b10 A
1-
#46000
b1001 5
b0 6
b1001 8
b1 +
b1 3
b1010 (
b1010 0
#50000
0-
#55000
b1001 $
b1001 >
b11 #
b11 ?
b1 "
b1 A
1-
#56000
b110101 6
b0 5
b111101 7
b111010 8
b110110 *
b110110 2
b111110 )
b111110 1
b111011 (
b111011 0
#60000
0-
#65000
b0 $
b0 >
b1001 #
b1001 ?
1-
